[
 {
  "id": 1,
  "name": "agua mineral",
  "brand": "glaciar",
  "price": "70",
  "discount": "50",
  "category": "almacen",
  "stock": "100",
  "image": "imageProduct-1605665664477.mp4"
 },
 {
  "id": 2,
  "name": "aceite",
  "brand": "marolio",
  "format": "500",
  "format2": "mililitro",
  "price": "300",
  "discount": "250",
  "category": "almacen",
  "stock": "10",
  "image": "imageProduct-1606061455897.png"
 },
 {
  "id": 3,
  "name": "yerba",
  "brand": "Cruz de Malta",
  "format": "500",
  "format2": "gramos",
  "price": "240",
  "discount": "200",
  "category": "almacen",
  "stock": "50",
  "image": "imageProduct-1606098344963.jpg"
 }
]